glassesbmi/bmi.py
glassesbmi-0.0.0.1.dist-info/METADATA
glassesbmi-0.0.0.1.dist-info/WHEEL
glassesbmi-0.0.0.1.dist-info/top_level.txt
glassesbmi-0.0.0.1.dist-info/RECORD
