Metadata-Version: 2.1
Name: glassesbmi
Version: 0.0.0.1
Summary: My First Test Pacakge
Home-page: https://google.com
Author: Gyungjun Ahn
Author-email: an4683@gmail.com
License: MIT
Platform: UNKNOWN
Requires-Python: >=3
